{
  "routingRules": {
    "description": "Smart routing rules to automatically select the best model for different question types",
    "rules": [
      {
        "name": "code_questions",
        "keywords": ["function", "code", "programming", "python", "javascript", "debug", "syntax", "class", "method", "algorithm"],
        "targetModel": "code_expert",
        "confidence": 0.9,
        "example": "Write a Python function to calculate factorial"
      },
      {
        "name": "concept_questions", 
        "keywords": ["explain", "what is", "how does", "concept", "theory", "definition", "understand", "meaning"],
        "targetModel": "concept_expert",
        "confidence": 0.8,
        "example": "Explain what recursion means in programming"
      },
      {
        "name": "practice_questions",
        "keywords": ["best practice", "recommendation", "should I", "guidelines", "advice", "tips", "optimize", "improve"],
        "targetModel": "practice_expert", 
        "confidence": 0.8,
        "example": "What are the best practices for writing clean code?"
      },
      {
        "name": "comprehensive_questions",
        "keywords": ["tutorial", "complete guide", "everything about", "full explanation", "step by step", "comprehensive"],
        "targetModel": "ask_all_experts",
        "confidence": 0.9,
        "example": "Give me a complete tutorial on Python functions"
      }
    ],
    "fallback": {
      "defaultModel": "concept_expert",
      "reason": "When no specific keywords match, use concept expert for general explanations"
    }
  },
  "examples": {
    "code_routing": {
      "input": "Write a function to reverse a string",
      "detected_keywords": ["function"],
      "selected_model": "code_expert",
      "reasoning": "Contains 'function' keyword, clearly a coding request"
    },
    "concept_routing": {
      "input": "Explain what machine learning is",
      "detected_keywords": ["explain", "what is"],
      "selected_model": "concept_expert", 
      "reasoning": "Contains 'explain' and 'what is', requesting conceptual understanding"
    },
    "practice_routing": {
      "input": "What are best practices for API design?",
      "detected_keywords": ["best practices"],
      "selected_model": "practice_expert",
      "reasoning": "Explicitly asks for best practices and guidelines"
    },
    "comprehensive_routing": {
      "input": "Give me a complete tutorial on Python functions with examples and best practices",
      "detected_keywords": ["complete", "tutorial", "examples", "best practices"],
      "selected_model": "ask_all_experts",
      "reasoning": "Requests comprehensive coverage requiring all three model types"
    }
  }
}
